surfari/__init__.py
surfari/navigation_cli.py
surfari/agents/__init__.py
surfari/agents/base_agent/__init__.py
surfari/agents/base_agent/_base_agent.py
surfari/agents/navigation_agent/__init__.py
surfari/agents/navigation_agent/_navigation_agent.py
surfari/agents/navigation_agent/_pinecone_resolver.py
surfari/agents/navigation_agent/_prompts.py
surfari/agents/navigation_agent/_record_and_replay.py
surfari/agents/navigation_agent/_record_and_replay_prompt.py
surfari/agents/navigation_agent/_typing.py
surfari/agents/navigation_agent/_value_resolver.py
surfari/agents/tools/google_tools.py
surfari/agents/tools/account_tool/_tool_definition.py
surfari/model/structured_llm.py
surfari/model/tool_executor.py
surfari/model/tool_helper.py
surfari/model/mcp/__init__.py
surfari/model/mcp/fs_http_embed.py
surfari/model/mcp/fs_server.py
surfari/model/mcp/load_mcp_servers.py
surfari/model/mcp/manager.py
surfari/model/mcp/mcp_config.json
surfari/model/mcp/mcp_types.py
surfari/model/mcp/session.py
surfari/model/mcp/tool_registry.py
surfari/security/.env
surfari/security/credentials.db
surfari/security/data_masker.py
surfari/security/gmail_otp_fetcher.py
surfari/security/site_credential_manager.py
surfari/uploads/testDocForUpload.docx
surfari/uploads/testDocForUpload.pdf
surfari/uploads/subfolder/testDocForUpload.txt
surfari/util/cdp_browser.py
surfari/util/config.json
surfari/util/config.py
surfari/util/db_service.py
surfari/util/electron_connector.py
surfari/util/playwright_util.py
surfari/util/surfari_logger.py
surfari/view/full_text_extractor.py
surfari/view/html_to_text.js
surfari/view/text_layouter.py
surfari-0.1.11.dist-info/METADATA
surfari-0.1.11.dist-info/WHEEL
surfari-0.1.11.dist-info/top_level.txt
surfari-0.1.11.dist-info/RECORD
